sleakops/__init__.py
sleakops/auth.py
sleakops/cli.py
sleakops/config.py
sleakops/api/__init__.py
sleakops/api/client.py
sleakops/commands/__init__.py
sleakops/commands/base.py
sleakops/commands/build.py
sleakops/commands/deploy.py
sleakops/commands/get_access_cluster.py
sleakops/commands/login.py
sleakops/commands/shell.py
sleakops-0.1.5.dist-info/METADATA
sleakops-0.1.5.dist-info/WHEEL
sleakops-0.1.5.dist-info/entry_points.txt
sleakops-0.1.5.dist-info/top_level.txt
sleakops-0.1.5.dist-info/RECORD
