Metadata-Version: 2.4
Name: sleakops
Version: 0.1.5
Summary: A CLI tool to build and deploy projects with Sleakops.
Project-URL: Documentation, https://docs.sleakops.com
Project-URL: App page, https://sleakops.com
Requires-Python: >=3.7
Requires-Dist: requests
Requires-Dist: click
Requires-Dist: PyJWT
Requires-Dist: PyYAML
